{
  "build": {
    "content": [
      {
        "files": [
          "**/*.{md,yml}"
        ],
        "exclude": [
          "_site/**"
        ]
      }
    ],
    "resource": [
      {
        "files": [
          "images/**"
        ]
      }
    ],
    "output": "_site",
    "template": [
      "default",
      "modern"
    ],
    "globalMetadata": {
      "_appName": "Unity_Projet3_Pendu",
      "_appTitle": "Unity_Projet3_Pendu",
      "_enableSearch": false,
      "pdf": true
    }
  }
}